bestdori/__init__.py
bestdori/bands.py
bestdori/cards.py
bestdori/characters.py
bestdori/charts.py
bestdori/comics.py
bestdori/costumes.py
bestdori/eventarchives.py
bestdori/events.py
bestdori/eventtop.py
bestdori/eventtracker.py
bestdori/exceptions.py
bestdori/festival.py
bestdori/gacha.py
bestdori/icon.py
bestdori/logincampaigns.py
bestdori/miracleticket.py
bestdori/missions.py
bestdori/player.py
bestdori/post.py
bestdori/settings.py
bestdori/skills.py
bestdori/songmeta.py
bestdori/songs.py
bestdori/stamps.py
bestdori/thumb.py
bestdori/typing.py
bestdori/upload.py
bestdori/user.py
bestdori/ayachan/__init__.py
bestdori/ayachan/chartmetrics.py
bestdori/ayachan/sonolus.py
bestdori/ayachan/typing.py
bestdori/data/api/bestdori/api.json
bestdori/data/api/bestdori/assets.json
bestdori/data/api/bestdori/res.json
bestdori/models/__init__.py
bestdori/models/content.py
bestdori/models/note.py
bestdori/utils/__init__.py
bestdori/utils/network/__init__.py
bestdori/utils/network/aiohttp.py
bestdori/utils/network/client.py
bestdori/utils/network/httpx.py
bestdori_api-2.2.0.dist-info/licenses/LICENSE
bestdori_api-2.2.0.dist-info/METADATA
bestdori_api-2.2.0.dist-info/WHEEL
bestdori_api-2.2.0.dist-info/top_level.txt
bestdori_api-2.2.0.dist-info/RECORD
