Metadata-Version: 2.4
Name: bestdori-api
Version: 2.2.0
Summary: Bestdori 的各种 API 调用整合，另外附带部分功能
Home-page: https://github.com/WindowsSov8forUs/bestdori-api
Author: WindowsSov8
Author-email: qwertyuiop2333@hotmail.com
License: MIT
Classifier: Programming Language :: Python :: 3.10
Classifier: License :: OSI Approved :: MIT License
Classifier: Operating System :: OS Independent
Requires-Python: >=3.10
License-File: LICENSE
Requires-Dist: typing_extensions>=4.5.0
Requires-Dist: multidict>=5.2.0
Requires-Dist: yarl>=1.7.0
Provides-Extra: httpx
Requires-Dist: httpx>=0.22.0; extra == "httpx"
Provides-Extra: aiohttp
Requires-Dist: aiohttp>=3.8.1; extra == "aiohttp"
Dynamic: author
Dynamic: author-email
Dynamic: classifier
Dynamic: description
Dynamic: description-content-type
Dynamic: home-page
Dynamic: license
Dynamic: license-file
Dynamic: provides-extra
Dynamic: requires-dist
Dynamic: requires-python
Dynamic: summary
